chatGPTKS/__init__.py
chatGPTKS/chatGPTKS.py
chatGPTKS-1.1.1.dist-info/METADATA
chatGPTKS-1.1.1.dist-info/WHEEL
chatGPTKS-1.1.1.dist-info/top_level.txt
chatGPTKS-1.1.1.dist-info/RECORD
