Metadata-Version: 2.1
Name: chatGPTKS
Version: 1.1.1
Summary: 这个包对api进行了封装，供公司内部使用
Author: HuntingGame
Author-email: 
